source_smartsheets/__init__.py
source_smartsheets/run.py
source_smartsheets/sheet.py
source_smartsheets/source.py
source_smartsheets/spec.json
source_smartsheets/streams.py
airbyte_source_smartsheets-1.1.46.dist-info/METADATA
airbyte_source_smartsheets-1.1.46.dist-info/WHEEL
airbyte_source_smartsheets-1.1.46.dist-info/entry_points.txt
airbyte_source_smartsheets-1.1.46.dist-info/RECORD
