Metadata-Version: 2.3
Name: airbyte-source-smartsheets
Version: 1.1.46
Summary: Source implementation for Smartsheets.
License: MIT
Author: Airbyte
Author-email: contact@airbyte.io
Requires-Python: >=3.9,<3.12
Classifier: License :: OSI Approved :: MIT License
Classifier: Programming Language :: Python :: 3
Classifier: Programming Language :: Python :: 3.9
Classifier: Programming Language :: Python :: 3.10
Classifier: Programming Language :: Python :: 3.11
Requires-Dist: airbyte-cdk (==0.80.0)
Requires-Dist: smartsheet-python-sdk (==2.177.1)
Requires-Dist: urllib3 (==1.26.18)
Project-URL: Documentation, https://docs.airbyte.com/integrations/sources/smartsheets
Project-URL: Homepage, https://airbyte.com
Project-URL: Repository, https://github.com/airbytehq/airbyte
